pyngen/__init__.py
pyngen/lib.py
pyngen/ngen_exceptions.py
pyngen/pyngen.py
pyngen-1.0.0.data/scripts/ngen
pyngen-1.0.0.dist-info/LICENSE
pyngen-1.0.0.dist-info/METADATA
pyngen-1.0.0.dist-info/WHEEL
pyngen-1.0.0.dist-info/top_level.txt
pyngen-1.0.0.dist-info/RECORD
