Metadata-Version: 2.1
Name: pyngen
Version: 1.0.0
Summary: Ngen REST. A python library for using Ngen
Home-page: https://github.com/CERTUNLP/pyngen
Author: CERTUNLP
Author-email: soporte@cert.unlp.edu.ar
Classifier: Programming Language :: Python :: 3
License-File: LICENSE
Requires-Dist: requests
Requires-Dist: filemime
Requires-Dist: click
Requires-Dist: python-slugify
